libcasm/casmglobal/__init__.py
libcasm/casmglobal/__main__.py
libcasm/casmglobal/_casmglobal.cpython-310-x86_64-linux-gnu.so
libcasm/counter/__init__.py
libcasm/counter/_counter.cpython-310-x86_64-linux-gnu.so
libcasm/include/casm/casm_io/FileData.hh
libcasm/include/casm/casm_io/FormatFlag.hh
libcasm/include/casm/casm_io/Help.hh
libcasm/include/casm/casm_io/Log.hh
libcasm/include/casm/casm_io/SafeOfstream.hh
libcasm/include/casm/casm_io/string_io.hh
libcasm/include/casm/casm_io/container/json_io.hh
libcasm/include/casm/casm_io/container/stream_io.hh
libcasm/include/casm/casm_io/dataformatter/DataFormatter.hh
libcasm/include/casm/casm_io/dataformatter/DataFormatterDecl.hh
libcasm/include/casm/casm_io/dataformatter/DataFormatterFilter.hh
libcasm/include/casm/casm_io/dataformatter/DataFormatterFilter_impl.hh
libcasm/include/casm/casm_io/dataformatter/DataFormatterTools.hh
libcasm/include/casm/casm_io/dataformatter/DataFormatterTools_impl.hh
libcasm/include/casm/casm_io/dataformatter/DataFormatter_impl.hh
libcasm/include/casm/casm_io/dataformatter/DataStream.hh
libcasm/include/casm/casm_io/dataformatter/DatumFormatterAdapter.hh
libcasm/include/casm/casm_io/dataformatter/EigenDataStream.hh
libcasm/include/casm/casm_io/dataformatter/FormattedDataFile.hh
libcasm/include/casm/casm_io/dataformatter/FormattedDataFile_impl.hh
libcasm/include/casm/casm_io/enum/io_traits.hh
libcasm/include/casm/casm_io/enum/json_io.hh
libcasm/include/casm/casm_io/enum/stream_io.hh
libcasm/include/casm/casm_io/json/InputParser.hh
libcasm/include/casm/casm_io/json/InputParser_impl.hh
libcasm/include/casm/casm_io/json/jsonFile.hh
libcasm/include/casm/casm_io/json/jsonParser.hh
libcasm/include/casm/casm_io/json/optional.hh
libcasm/include/casm/container/Array.hh
libcasm/include/casm/container/BaseCounter.hh
libcasm/include/casm/container/ContainerTraits.hh
libcasm/include/casm/container/Counter.hh
libcasm/include/casm/container/IsoCounter.hh
libcasm_global-2.3.0.dist-info/METADATA
libcasm_global-2.3.0.dist-info/WHEEL
libcasm_global-2.3.0.dist-info/top_level.txt
libcasm_global-2.3.0.dist-info/RECORD
libcasm_global-2.3.0.dist-info/licenses/LICENSE
